tkcode/__init__.py
tkcode/codeblock.py
tkcode/codebox.py
tkcode/codeeditor.py
tkcode/schemes/azure.json
tkcode/schemes/dracula.json
tkcode/schemes/mariana.json
tkcode/schemes/monokai-plus-plus.json
tkcode/schemes/monokai.json
tkcode-0.1.6.dist-info/LICENSE
tkcode-0.1.6.dist-info/METADATA
tkcode-0.1.6.dist-info/WHEEL
tkcode-0.1.6.dist-info/top_level.txt
tkcode-0.1.6.dist-info/RECORD
