Metadata-Version: 2.1
Name: tkcode
Version: 0.1.6
Summary: A code editor and code block widget for tkinter with syntax highlighting, and some other useful stuff
Home-page: https://github.com/rdbende/tkcode
Author: rdbende
Author-email: rdbende@gmail.com
License: MIT license
Platform: UNKNOWN
Classifier: Programming Language :: Python :: 3.6
Classifier: License :: OSI Approved :: MIT License
Classifier: Operating System :: OS Independent
Requires-Python: >=3.6
Requires-Dist: pygments
